mmrelay/__init__.py
mmrelay/__main__.py
mmrelay/cli.py
mmrelay/cli_utils.py
mmrelay/config.py
mmrelay/db_runtime.py
mmrelay/db_utils.py
mmrelay/e2ee_utils.py
mmrelay/log_utils.py
mmrelay/main.py
mmrelay/matrix_utils.py
mmrelay/meshtastic_utils.py
mmrelay/message_queue.py
mmrelay/plugin_loader.py
mmrelay/runtime_utils.py
mmrelay/setup_utils.py
mmrelay/windows_utils.py
mmrelay/constants/__init__.py
mmrelay/constants/app.py
mmrelay/constants/cli.py
mmrelay/constants/config.py
mmrelay/constants/database.py
mmrelay/constants/formats.py
mmrelay/constants/messages.py
mmrelay/constants/network.py
mmrelay/constants/plugins.py
mmrelay/constants/queue.py
mmrelay/plugins/__init__.py
mmrelay/plugins/base_plugin.py
mmrelay/plugins/debug_plugin.py
mmrelay/plugins/drop_plugin.py
mmrelay/plugins/health_plugin.py
mmrelay/plugins/help_plugin.py
mmrelay/plugins/map_plugin.py
mmrelay/plugins/mesh_relay_plugin.py
mmrelay/plugins/nodes_plugin.py
mmrelay/plugins/ping_plugin.py
mmrelay/plugins/telemetry_plugin.py
mmrelay/plugins/weather_plugin.py
mmrelay/tools/__init__.py
mmrelay/tools/mmrelay.service
mmrelay/tools/sample-docker-compose-prebuilt.yaml
mmrelay/tools/sample-docker-compose.yaml
mmrelay/tools/sample.env
mmrelay/tools/sample_config.yaml
mmrelay-1.2.11.dist-info/licenses/LICENSE
mmrelay-1.2.11.dist-info/METADATA
mmrelay-1.2.11.dist-info/WHEEL
mmrelay-1.2.11.dist-info/entry_points.txt
mmrelay-1.2.11.dist-info/top_level.txt
mmrelay-1.2.11.dist-info/RECORD
