Metadata-Version: 2.4
Name: mmrelay
Version: 1.2.11
Summary: Bridge between Meshtastic mesh networks and Matrix chat rooms
Home-page: https://github.com/jeremiah-k/meshtastic-matrix-relay
Author: Geoff Whittington, Jeremiah K., and contributors
Author-email: jeremiahk@gmx.com
Project-URL: Bug Tracker, https://github.com/jeremiah-k/meshtastic-matrix-relay/issues
Classifier: Programming Language :: Python :: 3
Classifier: Programming Language :: Python :: 3.10
Classifier: Programming Language :: Python :: 3.11
Classifier: Programming Language :: Python :: 3.12
Classifier: License :: OSI Approved :: GNU General Public License v3 or later (GPLv3+)
Classifier: Operating System :: OS Independent
Classifier: Development Status :: 4 - Beta
Classifier: Topic :: Communications
Requires-Python: >=3.10
License-File: LICENSE
Requires-Dist: meshtastic>=2.7.4
Requires-Dist: Pillow==12.1.0
Requires-Dist: matrix-nio==0.25.2
Requires-Dist: matplotlib==3.10.8
Requires-Dist: requests==2.32.5
Requires-Dist: markdown==3.10.1
Requires-Dist: bleach==6.3.0
Requires-Dist: haversine==2.9.0
Requires-Dist: schedule==1.2.2
Requires-Dist: platformdirs==4.5.1
Requires-Dist: py-staticmaps>=0.4.0
Requires-Dist: psutil>=5.8.0
Requires-Dist: rich==14.3.1
Requires-Dist: setuptools>=80.9.0
Provides-Extra: dev
Requires-Dist: pyright==1.1.408; extra == "dev"
Requires-Dist: mypy==1.19.1; extra == "dev"
Requires-Dist: types-PyYAML==6.0.12.20250915; extra == "dev"
Requires-Dist: types-Markdown==3.10.0.20251106; extra == "dev"
Provides-Extra: e2e
Requires-Dist: matrix-nio[e2e]==0.25.2; extra == "e2e"
Requires-Dist: python-olm; extra == "e2e"
Dynamic: author
Dynamic: author-email
Dynamic: classifier
Dynamic: description
Dynamic: description-content-type
Dynamic: home-page
Dynamic: license-file
Dynamic: project-url
Dynamic: provides-extra
Dynamic: requires-dist
Dynamic: requires-python
Dynamic: summary
